[
	{
		"name": "CrossRef Lookup",
		"alias": "CrossRef",
		"_urlTemplate": "https://crossref.org/openurl?{z:openURL}&pid=zter:zter321",
		"description": "CrossRef Search Engine",
		"hidden": false,
		"_urlParams": [],
		"_urlNamespaces": {
			"z": "http://www.zotero.org/namespaces/openSearch#",
			"": "http://a9.com/-/spec/opensearch/1.1/"
		},
		"_iconSourceURI": "https://crossref.org/favicon.ico"
	},
	{
		"name": "Google Scholar Search",
		"alias": "Google Scholar",
		"_urlTemplate": "https://scholar.google.com/scholar?as_q=&as_epq={z:title}&as_occt=title&as_sauthors={rft:aufirst?}+{rft:aulast?}&as_ylo={z:year?}&as_yhi={z:year?}&as_sdt=1.&as_sdtp=on&as_sdtf=&as_sdts=22&",
		"description": "Google Scholar Search",
		"hidden": false,
		"_urlParams": [],
		"_urlNamespaces": {
			"rft": "info:ofi/fmt:kev:mtx:journal",
			"z": "http://www.zotero.org/namespaces/openSearch#",
			"": "http://a9.com/-/spec/opensearch/1.1/"
		},
		"_iconSourceURI": "https://scholar.google.com/favicon.ico"
	},
	{
		"_name": "CNKI Search",
		"_alias": "CNKI",
		"_description": "CNKI",
		"_icon": "https://www.cnki.net/favicon.ico",
		"_hidden": false,
		"_urlTemplate": "https://kns.cnki.net/kns8/defaultresult/index?korder=TI&kw={z:title}",
		"_urlParams": [],
		"_urlNamespaces": {
			"rft": "info:ofi/fmt:kev:mtx:journal",
			"z": "http://www.zotero.org/namespaces/openSearch#",
			"": "http://a9.com/-/spec/opensearch/1.1/"
		},
		"_iconSourceURI": "https://www.cnki.net/favicon.ico"
	},
	{
		"_name": "Sci-Hub DOI Search",
		"_alias": "Sci-Hub DOI",
		"_description": "SciHub Lookup Lookup",
		"_icon": "http://sci-hub.tw/favicon.ico",
		"_hidden": false,
		"_urlTemplate": "http://sci-hub.tw/{z:DOI}",
		"_urlParams": [],
		"_urlNamespaces": {
			"z": "http://www.zotero.org/namespaces/openSearch#"
		},
		"_iconSourceURI": "http://sci-hub.tw/favicon.ico"
	},
	{
		"_name": "Web of Science Search",
		"_alias": "WOS",
		"_description": "Web of Science Search",
		"_icon": "http://login.webofknowledge.com/error/WOK5/images/wok_favicon.ico",
		"_hidden": false,
		"_urlTemplate": "http://ws.isiknowledge.com/cps/openurl/service?url_ver=Z39.88-2004&{z:openURL}",
		"_urlParams": [],
		"_urlNamespaces": {
			"rft": "info:ofi/fmt:kev:mtx:journal",
			"z": "http://www.zotero.org/namespaces/openSearch#"
		},
		"_iconSourceURI": "http://login.webofknowledge.com/error/WOK5/images/wok_favicon.ico"
	},
	{
		"_name": "ScienceDirect",
		"_alias": "SDS",
		"_description": "ScienceDirect Search",
		"_icon": "https://www.sciencedirect.com/favicon.ico",
		"_hidden": false,
		"_urlTemplate": "https://www.sciencedirect.com/search?qs={z:title}",
		"_urlParams": [],
		"_urlNamespaces": {
			"rft": "info:ofi/fmt:kev:mtx:journal",
			"z": "http://www.zotero.org/namespaces/openSearch#"
		},
		"_iconSourceURI": "https://www.sciencedirect.com/favicon.ico"
	}
]
